{
  "companyName": "ELLAH LAKES PLC",
  "rcNumber": null,
  "reportTitle": "Statement of comprehensive income for 9 months ended April 30, 2015",
  "consolidationLevel": null,
  "statementType": null,
  "financialPeriodLabel": "9 Months ended April 30, 2015",
  "periodStart": "2015-01-01",
  "periodEnd": "2015-04-30",
  "periodLengthMonths": 4,
  "fiscalYear": 2015,
  "auditedStatus": null,
  "currency": "NGN",
  "chunkPage": 1,
  "topics": [],
  "keyFigures": {
    "totalAssets": 1189370040,
    "totalLiabilities": null,
    "totalEquity": null,
    "revenue": 37025205,
    "costOfSales": 24078708,
    "grossProfit": 127151868,
    "operatingProfitLoss": null,
    "netProfit": -27574277,
    "eps": -0.237,
    "cashAndCashEquivalents": 6081611,
    "cashAtBank": null,
    "biologicalAssets": null,
    "propertyPlantEquipment": null,
    "borrowings": null,
    "retainedEarnings": null,
    "shareCapital": null,
    "sharePremium": null,
    "revaluationSurplus": null
  },
  "detailed_summary": "**Financial Summary for Ellah Lakes PLC**\n\n**Statement of Financial Position as of April 30, 2015 and July 31, 2014:**\n- **Total Assets:**\n  - April 30, 2015: N1,189,370,040\n  - July 31, 2014: N1,195,440,666\n- **Non-Current Assets:**\n  - April 30, 2015: N1,144,864,339\n  - July 31, 2014: N1,151,280,801\n- **Current Assets:**\n  - April 30, 2015: N44,505,701\n  - July 31, 2014: N44,159,865\n- **Total Liabilities:**\n  - April 30, 2015: N622,609,889\n  - July 31, 2014: N614,475,144\n- **Members' Equity:**\n  - April 30, 2015: N566,760,151\n  - July 31, 2014: N580,965,522\n\n**Statement of Comprehensive Income for the 9 months ended April 30, 2015:**\n- **Sales Revenue:**\n  - N37,025,205\n- **Cost of Sales:**\n  - N24,078,708\n- **Gross Profit:**\n  - N12,946,497\n- **Operating Expenses:**\n  - N27,151,868\n- **Profit/Loss Before Taxation:**\n  - N(14,205,371)\n- **Net Profit/Loss:**\n  - N(27,574,277)\n- **Earnings Per Share (EPS):**\n  - N(0.237)\n\n**Statement of Cash Flows for the 9 months ended April 30, 2015:**\n- **Cash Flows from Operating Activities:**\n  - Cash receipts from customers: N37,025,205\n  - Cash paid to suppliers and employees: N(24,078,708)\n  - Net cash inflow from operating activities: N(14,205,371)\n- **Cash Flows from Investing Activities:**\n  - Purchase of property, plant, and equipment: N6,081,611\n- **Cash Flows from Financing Activities:**\n  - Proceeds from long-term borrowings: N18,369,800\n  - Net cash inflow from financing activities: N18,369,800\n- **Net Cash Increase:**\n  - Cash and cash equivalents at beginning of period: N2,306,569\n  - Cash and cash equivalents at end of period: N6,081,611\n\nThis summary encapsulates the key financial figures and performance metrics for Ellah Lakes PLC for the periods ending April 30, 2015, and July 31, 2014, providing a comprehensive overview of the company's financial health."
}